groq_eval/__init__.py
groq_eval/evaluator.py
groq_eval_score-0.2.0.dist-info/licenses/LICENSE
groq_eval_score-0.2.0.dist-info/METADATA
groq_eval_score-0.2.0.dist-info/WHEEL
groq_eval_score-0.2.0.dist-info/top_level.txt
groq_eval_score-0.2.0.dist-info/RECORD
